adyeno/__init__.py
adyeno/exceptions.py
adyeno/pytransform/__init__.py
adyeno/pytransform/_pytransform.dll
adyeno/pytransform/pytransform.dylib
adyeno/pytransform/platforms/darwin/x86_64/_pytransform.dylib
adyeno/pytransform/platforms/windows/x86_64/_pytransform.dll
adyeno-0.3.dist-info/METADATA
adyeno-0.3.dist-info/WHEEL
adyeno-0.3.dist-info/top_level.txt
adyeno-0.3.dist-info/RECORD
